fastapi_ai_chat/__init__.py
fastapi_ai_chat/app.py
fastapi_ai_chat/providers.py
fastapi_ai_chat/sqlite_memory.py
fastapi_ai_chat/types.py
fastapi_ai_chat-1.0.2.dist-info/licenses/LICENSE
fastapi_ai_chat-1.0.2.dist-info/METADATA
fastapi_ai_chat-1.0.2.dist-info/WHEEL
fastapi_ai_chat-1.0.2.dist-info/top_level.txt
fastapi_ai_chat-1.0.2.dist-info/RECORD
