Metadata-Version: 2.4
Name: fastapi-ai-chat
Version: 1.0.2
Summary: Minimal FastAPI backend for streaming AI chat over SSE (token/done/error), compatible with ai-chat-kit
Author: Your Name
License: MIT License
Project-URL: Homepage, https://pypi.org/project/fastapi-ai-chat/
Keywords: ai,chat,fastapi,sse,streaming
Classifier: Development Status :: 3 - Alpha
Classifier: Intended Audience :: Developers
Classifier: License :: OSI Approved :: MIT License
Classifier: Programming Language :: Python :: 3
Classifier: Programming Language :: Python :: 3 :: Only
Classifier: Programming Language :: Python :: 3.10
Classifier: Programming Language :: Python :: 3.11
Classifier: Programming Language :: Python :: 3.12
Classifier: Framework :: FastAPI
Classifier: Topic :: Software Development :: Libraries
Requires-Python: >=3.10
License-File: LICENSE
Requires-Dist: fastapi>=0.110.0
Requires-Dist: httpx>=0.27.0
Provides-Extra: server
Requires-Dist: uvicorn[standard]>=0.23.0; extra == "server"
Dynamic: license-file
